tkutils/__init__.py
tkutils/__main__.py
tkutils/__version__.py
tkutils/grid_layout.py
tkutils/helpers/__init__.py
tkutils/helpers/event_provider.py
tkutils/helpers/keysym.py
tkutils/images.py
tkutils/menu_builder/__init__.py
tkutils/menu_builder/bases.py
tkutils/menu_builder/menu_builder.py
tkutils/menu_builder/menu_builder_options.py
tkutils/two_way_binding/__init__.py
tkutils/two_way_binding/binder.py
tkutils/two_way_binding/binding_descriptor.py
tkutils/two_way_binding/configuration/__init__.py
tkutils/two_way_binding/configuration/_binder_config.py
tkutils/two_way_binding/configuration/_configuration.py
tkutils/two_way_binding/configuration/_configurer_image_factory.py
tkutils/two_way_binding/errors.py
tkutils/utilities/__init__.py
tkutils/utilities/singleton_namespace.py
tkutils-1.1.2.dist-info/METADATA
tkutils-1.1.2.dist-info/WHEEL
tkutils-1.1.2.dist-info/entry_points.txt
tkutils-1.1.2.dist-info/RECORD
