Metadata-Version: 2.1
Name: tkutils
Version: 1.1.2
Summary: Python tkinter utilities.
Home-page: http://frederic-zinelli.gitlab.io/tkutils/
Author: Frédéric Zinelli
Author-email: frederic.zinelli@gmail.com
Requires-Python: >=3.8,<4.0
Classifier: Programming Language :: Python :: 3
Classifier: Programming Language :: Python :: 3.8
Classifier: Programming Language :: Python :: 3.9
Classifier: Programming Language :: Python :: 3.10
Classifier: Programming Language :: Python :: 3.11
Requires-Dist: Pillow (>=9.3,<10.0)
Requires-Dist: typing-extensions (>=4.4,<5.0)
Project-URL: Repository, https://gitlab.com/frederic-zinelli/tkutils
